tinytable/__init__.py
tinytable/column.py
tinytable/csv.py
tinytable/excel.py
tinytable/filter.py
tinytable/group.py
tinytable/iloc.py
tinytable/row.py
tinytable/sqlite.py
tinytable/table.py
tinytable/types.py
tinytable/functional/__init__.py
tinytable/functional/columns.py
tinytable/functional/copy.py
tinytable/functional/edit.py
tinytable/functional/features.py
tinytable/functional/filter.py
tinytable/functional/group.py
tinytable/functional/join.py
tinytable/functional/na.py
tinytable/functional/rows.py
tinytable/functional/utils.py
tinytable/functional/validate.py
tinytable-0.17.0.dist-info/LICENSE.md
tinytable-0.17.0.dist-info/METADATA
tinytable-0.17.0.dist-info/WHEEL
tinytable-0.17.0.dist-info/top_level.txt
tinytable-0.17.0.dist-info/RECORD
